yreport/__init__.py
yreport/health.py
yreport/recommend.py
yreport/report.py
yreport/sklearn.py
yreport/types.py
yreport-0.1.3.dist-info/licenses/LICENSE
yreport-0.1.3.dist-info/METADATA
yreport-0.1.3.dist-info/WHEEL
yreport-0.1.3.dist-info/top_level.txt
yreport-0.1.3.dist-info/RECORD
