Metadata-Version: 2.4
Name: yreport
Version: 0.1.3
Summary: Dataset-agnostic data health report for tabular datasets
Author-email: Yogesh Kardile <kardile.work@gmail.com>
License: MIT
Project-URL: Homepage, https://github.com/Yogesh942134/yreport
Project-URL: Repository, https://github.com/Yogesh942134/yreport
Classifier: Programming Language :: Python :: 3
Classifier: License :: OSI Approved :: MIT License
Classifier: Operating System :: OS Independent
Requires-Python: >=3.9
License-File: LICENSE
Requires-Dist: pandas>=1.5
Requires-Dist: numpy>=1.21
Requires-Dist: scipy
Requires-Dist: scikit-learn
Dynamic: license-file
